rombo_appian/__init__.py
rombo_appian/utils/__init__.py
rombo_appian/utils/components/ButtonUtils.py
rombo_appian/utils/components/ComponentUtils.py
rombo_appian/utils/components/DateUtils.py
rombo_appian/utils/components/DropdownUtils.py
rombo_appian/utils/components/InputUtils.py
rombo_appian/utils/components/LabelUtils.py
rombo_appian/utils/components/LinkUtils.py
rombo_appian/utils/components/TabUtils.py
rombo_appian/utils/components/TableUtils.py
rombo_appian/utils/components/__init__.py
rombo_appian/utils/controllers/ComponentDriver.py
rombo_appian/utils/controllers/__init__.py
rombo_appian/utils/exceptions/MyCustomError.py
rombo_appian/utils/exceptions/__init__.py
rombo_appian-0.0.1.dist-info/licenses/LICENSE
rombo_appian-0.0.1.dist-info/METADATA
rombo_appian-0.0.1.dist-info/WHEEL
rombo_appian-0.0.1.dist-info/top_level.txt
rombo_appian-0.0.1.dist-info/RECORD
